{
  "first": {
    "data": {
      "type": "Feature",
      "properties": {},
      "geometry": {
        "type": "Polygon",
        "coordinates": [
          [
            [
              444.973594,
              56.452235
            ],
            [
              444.973594,
              56.454739
            ],
            [
              444.978417,
              56.454739
            ],
            [
              444.978417,
              56.452235
            ],
            [
              444.973594,
              56.452235
            ]
          ]
        ]
      }
    },
    "name": "First"
  }
}
